{"v":3,"stories":{"introduction--docs":{"id":"introduction--docs","title":"Introduction","name":"Docs","importPath":"./stories/Introduction.mdx","storiesImports":[],"tags":["unattached-mdx","docs"],"kind":"Introduction","story":"Docs","parameters":{"__id":"introduction--docs","docsOnly":true,"fileName":"./stories/Introduction.mdx"}},"border--docs":{"id":"border--docs","title":"Border","name":"Docs","importPath":"./stories/Border.mdx","storiesImports":["./stories/Border.stories.jsx"],"tags":["attached-mdx","docs"],"kind":"Border","story":"Docs","parameters":{"__id":"border--docs","docsOnly":true,"fileName":"./stories/Border.mdx"}},"color--docs":{"id":"color--docs","title":"Color","name":"Docs","importPath":"./stories/Color.mdx","storiesImports":["./stories/Color.stories.jsx"],"tags":["attached-mdx","docs"],"kind":"Color","story":"Docs","parameters":{"__id":"color--docs","docsOnly":true,"fileName":"./stories/Color.mdx"}},"font--docs":{"id":"font--docs","title":"Font","name":"Docs","importPath":"./stories/Font.mdx","storiesImports":["./stories/Font.stories.jsx"],"tags":["attached-mdx","docs"],"kind":"Font","story":"Docs","parameters":{"__id":"font--docs","docsOnly":true,"fileName":"./stories/Font.mdx"}},"icon--docs":{"id":"icon--docs","title":"Icon","name":"Docs","importPath":"./stories/Icon.mdx","storiesImports":["./stories/Icon.stories.jsx"],"tags":["attached-mdx","docs"],"kind":"Icon","story":"Docs","parameters":{"__id":"icon--docs","docsOnly":true,"fileName":"./stories/Icon.mdx"}},"shadow--docs":{"id":"shadow--docs","title":"Shadow","name":"Docs","importPath":"./stories/Shadow.mdx","storiesImports":["./stories/Shadow.stories.jsx"],"tags":["attached-mdx","docs"],"kind":"Shadow","story":"Docs","parameters":{"__id":"shadow--docs","docsOnly":true,"fileName":"./stories/Shadow.mdx"}},"spacing--docs":{"id":"spacing--docs","title":"Spacing","name":"Docs","importPath":"./stories/Spacing.mdx","storiesImports":["./stories/Spacing.stories.jsx"],"tags":["attached-mdx","docs"],"kind":"Spacing","story":"Docs","parameters":{"__id":"spacing--docs","docsOnly":true,"fileName":"./stories/Spacing.mdx"}},"border--width":{"id":"border--width","name":"Width","title":"Border","importPath":"./stories/Border.stories.jsx","tags":["story"],"kind":"Border","story":"Width","parameters":{"__id":"border--width","docsOnly":false,"fileName":"./stories/Border.stories.jsx"}},"border--radius":{"id":"border--radius","name":"Radius","title":"Border","importPath":"./stories/Border.stories.jsx","tags":["story"],"kind":"Border","story":"Radius","parameters":{"__id":"border--radius","docsOnly":false,"fileName":"./stories/Border.stories.jsx"}},"color--primary":{"id":"color--primary","name":"Primary","title":"Color","importPath":"./stories/Color.stories.jsx","tags":["story"],"kind":"Color","story":"Primary","parameters":{"__id":"color--primary","docsOnly":false,"fileName":"./stories/Color.stories.jsx"}},"color--grey":{"id":"color--grey","name":"Grey","title":"Color","importPath":"./stories/Color.stories.jsx","tags":["story"],"kind":"Color","story":"Grey","parameters":{"__id":"color--grey","docsOnly":false,"fileName":"./stories/Color.stories.jsx"}},"color--static":{"id":"color--static","name":"Static","title":"Color","importPath":"./stories/Color.stories.jsx","tags":["story"],"kind":"Color","story":"Static","parameters":{"__id":"color--static","docsOnly":false,"fileName":"./stories/Color.stories.jsx"}},"font--family":{"id":"font--family","name":"Family","title":"Font","importPath":"./stories/Font.stories.jsx","tags":["story"],"kind":"Font","story":"Family","parameters":{"__id":"font--family","docsOnly":false,"fileName":"./stories/Font.stories.jsx"}},"font--size":{"id":"font--size","name":"Size","title":"Font","importPath":"./stories/Font.stories.jsx","tags":["story"],"kind":"Font","story":"Size","parameters":{"__id":"font--size","docsOnly":false,"fileName":"./stories/Font.stories.jsx"}},"font--weight":{"id":"font--weight","name":"Weight","title":"Font","importPath":"./stories/Font.stories.jsx","tags":["story"],"kind":"Font","story":"Weight","parameters":{"__id":"font--weight","docsOnly":false,"fileName":"./stories/Font.stories.jsx"}},"font--line-height":{"id":"font--line-height","name":"Line Height","title":"Font","importPath":"./stories/Font.stories.jsx","tags":["story"],"kind":"Font","story":"Line Height","parameters":{"__id":"font--line-height","docsOnly":false,"fileName":"./stories/Font.stories.jsx"}},"font--letter-spacing":{"id":"font--letter-spacing","name":"Letter Spacing","title":"Font","importPath":"./stories/Font.stories.jsx","tags":["story"],"kind":"Font","story":"Letter Spacing","parameters":{"__id":"font--letter-spacing","docsOnly":false,"fileName":"./stories/Font.stories.jsx"}},"icon--icon":{"id":"icon--icon","name":"Icon","title":"Icon","importPath":"./stories/Icon.stories.jsx","tags":["story"],"kind":"Icon","story":"Icon","parameters":{"__id":"icon--icon","docsOnly":false,"fileName":"./stories/Icon.stories.jsx"}},"shadow--shadow":{"id":"shadow--shadow","name":"Shadow","title":"Shadow","importPath":"./stories/Shadow.stories.jsx","tags":["story"],"kind":"Shadow","story":"Shadow","parameters":{"__id":"shadow--shadow","docsOnly":false,"fileName":"./stories/Shadow.stories.jsx"}},"spacing--spacing":{"id":"spacing--spacing","name":"Spacing","title":"Spacing","importPath":"./stories/Spacing.stories.jsx","tags":["story"],"kind":"Spacing","story":"Spacing","parameters":{"__id":"spacing--spacing","docsOnly":false,"fileName":"./stories/Spacing.stories.jsx"}}}}
